wlhosted/__init__.py
wlhosted/addons.py
wlhosted/data.py
wlhosted/dbrouter.py
wlhosted/models.py
wlhosted/settings_test.py
wlhosted/integrations/__init__.py
wlhosted/integrations/forms.py
wlhosted/integrations/models.py
wlhosted/integrations/tasks.py
wlhosted/integrations/tests.py
wlhosted/integrations/utils.py
wlhosted/integrations/views.py
wlhosted/integrations/management/__init__.py
wlhosted/integrations/management/commands/__init__.py
wlhosted/integrations/management/commands/list_contacts.py
wlhosted/integrations/management/commands/list_payments.py
wlhosted/integrations/management/commands/migrate_payments.py
wlhosted/integrations/management/commands/push_users.py
wlhosted/integrations/templates/accounts/snippets/login-about.html
wlhosted/integrations/templates/hosted/create.html
wlhosted/integrations/templates/mail/billing_paid.html
wlhosted/integrations/templates/mail/billing_paid_subject.txt
wlhosted/locale/django.pot
wlhosted/locale/ab/LC_MESSAGES/django.po
wlhosted/locale/af/LC_MESSAGES/django.po
wlhosted/locale/afh/LC_MESSAGES/django.po
wlhosted/locale/ang/LC_MESSAGES/django.po
wlhosted/locale/ar/LC_MESSAGES/django.po
wlhosted/locale/ar_LY/LC_MESSAGES/django.po
wlhosted/locale/ars/LC_MESSAGES/django.po
wlhosted/locale/ast/LC_MESSAGES/django.po
wlhosted/locale/awa/LC_MESSAGES/django.po
wlhosted/locale/az/LC_MESSAGES/django.po
wlhosted/locale/ba/LC_MESSAGES/django.po
wlhosted/locale/bar/LC_MESSAGES/django.po
wlhosted/locale/be/LC_MESSAGES/django.po
wlhosted/locale/be_Latn/LC_MESSAGES/django.po
wlhosted/locale/ber/LC_MESSAGES/django.po
wlhosted/locale/bg/LC_MESSAGES/django.po
wlhosted/locale/bn/LC_MESSAGES/django.po
wlhosted/locale/bn_BD/LC_MESSAGES/django.po
wlhosted/locale/bnt/LC_MESSAGES/django.po
wlhosted/locale/bo/LC_MESSAGES/django.po
wlhosted/locale/br/LC_MESSAGES/django.po
wlhosted/locale/ca/LC_MESSAGES/django.po
wlhosted/locale/ce/LC_MESSAGES/django.po
wlhosted/locale/chn/LC_MESSAGES/django.po
wlhosted/locale/ckb/LC_MESSAGES/django.po
wlhosted-2026.1.dist-info/licenses/LICENSE
wlhosted-2026.1.dist-info/METADATA
wlhosted-2026.1.dist-info/WHEEL
wlhosted-2026.1.dist-info/top_level.txt
wlhosted-2026.1.dist-info/zip-safe
wlhosted-2026.1.dist-info/RECORD
