Metadata-Version: 2.4
Name: wlhosted
Version: 2026.1
Summary: Hosted Weblate Customization
Author-email: Michal Čihař <michal@weblate.org>
License-Expression: GPL-3.0-or-later
Project-URL: Documentation, https://docs.weblate.org/
Project-URL: Download, https://github.com/WeblateOrg/hosted
Project-URL: Homepage, https://weblate.org/
Project-URL: Issue Tracker, https://github.com/WeblateOrg/hosted/issues
Project-URL: Source Code, https://github.com/WeblateOrg/hosted
Project-URL: Twitter, https://twitter.com/WeblateOrg
Keywords: i18n,l10n,gettext,git,mercurial,translate
Classifier: Development Status :: 5 - Production/Stable
Classifier: Environment :: Web Environment
Classifier: Framework :: Django
Classifier: Intended Audience :: Developers
Classifier: Intended Audience :: System Administrators
Classifier: Operating System :: OS Independent
Classifier: Programming Language :: Python
Classifier: Programming Language :: Python :: 3
Classifier: Programming Language :: Python :: 3 :: Only
Classifier: Programming Language :: Python :: 3.12
Classifier: Programming Language :: Python :: 3.13
Classifier: Programming Language :: Python :: 3.14
Classifier: Topic :: Software Development :: Internationalization
Classifier: Topic :: Software Development :: Localization
Classifier: Topic :: Internet :: WWW/HTTP
Classifier: Topic :: Internet :: WWW/HTTP :: Dynamic Content
Requires-Python: >=3.12
License-File: LICENSE
Requires-Dist: Django<6.1,>=5.2
Requires-Dist: django-appconf>=1.0
Requires-Dist: django-countries==8.2.0
Requires-Dist: django-vies==6.2.2
Requires-Dist: fakturace==0.7.2
Requires-Dist: psycopg[binary]
Requires-Dist: python-dateutil
Requires-Dist: requests
Requires-Dist: Weblate>=5.5.3
Dynamic: license-file
